dingtalk/__init__.py
dingtalk/api/__init__.py
dingtalk/api/base.py
dingtalk/api/rest/CcoserviceServicegroupAddmemberRequest.py
dingtalk/api/rest/CcoserviceServicegroupGetRequest.py
dingtalk/api/rest/CorpBlazersGetbinddataRequest.py
dingtalk/api/rest/CorpBlazersGetbizidRequest.py
dingtalk/api/rest/CorpBlazersRemovemappingRequest.py
dingtalk/api/rest/CorpBlazersUnbindRequest.py
dingtalk/api/rest/CorpCalendarCreateRequest.py
dingtalk/api/rest/CorpChatbotAddchatbotinstanceRequest.py
dingtalk/api/rest/CorpChatbotCreateorgbotRequest.py
dingtalk/api/rest/CorpChatbotInstallRequest.py
dingtalk/api/rest/CorpChatbotListbychatbotidsRequest.py
dingtalk/api/rest/CorpChatbotListorgbotRequest.py
dingtalk/api/rest/CorpChatbotListorgbotbytypeandbottypeRequest.py
dingtalk/api/rest/CorpChatbotUpdatebychatbotidRequest.py
dingtalk/api/rest/CorpChatbotUpdateorgbotRequest.py
dingtalk/api/rest/CorpConversationCorpconversionGetconversationRequest.py
dingtalk/api/rest/CorpConversationCorpconversionListmemberRequest.py
dingtalk/api/rest/CorpDeptgroupSyncuserRequest.py
dingtalk/api/rest/CorpDeviceManageGetRequest.py
dingtalk/api/rest/CorpDeviceManageHasbinddeviceRequest.py
dingtalk/api/rest/CorpDeviceManageQuerylistRequest.py
dingtalk/api/rest/CorpDeviceManageUnbindRequest.py
dingtalk/api/rest/CorpDeviceNickUpdateRequest.py
dingtalk/api/rest/CorpDingCreateRequest.py
dingtalk/api/rest/CorpDingReceiverstatusListRequest.py
dingtalk/api/rest/CorpDingTaskCreateRequest.py
dingtalk/api/rest/CorpEmpSearchRequest.py
dingtalk/api/rest/CorpEncryptionKeyListRequest.py
dingtalk/api/rest/CorpExtAddRequest.py
dingtalk/api/rest/CorpExtListRequest.py
dingtalk/api/rest/CorpExtListlabelgroupsRequest.py
dingtalk/api/rest/CorpExtUpdateRequest.py
dingtalk/api/rest/CorpExtcontactCreateRequest.py
dingtalk/api/rest/CorpExtcontactDeleteRequest.py
dingtalk/api/rest/CorpExtcontactGetRequest.py
dingtalk/api/rest/CorpExtcontactListRequest.py
dingtalk/api/rest/CorpExtcontactListlabelgroupsRequest.py
ding_talk_wb-1.0.1.dist-info/METADATA
ding_talk_wb-1.0.1.dist-info/WHEEL
ding_talk_wb-1.0.1.dist-info/top_level.txt
ding_talk_wb-1.0.1.dist-info/RECORD
