Metadata-Version: 2.1
Name: ding-talk-wb
Version: 1.0.1
Summary: Reseal DingDing Talk
Home-page: https://github.com/spxinjie6/dingTalk.git
Author: spxinjie6
Author-email: 1311855817@qq.com
License: MIT
Keywords: dingding,ding-talk
Platform: UNKNOWN
